mcp_server_sis/__init__.py
mcp_server_sis/__main__.py
mcp_server_sis/sis.py
mcp_server_sis/sis_system.py
mcp_server_sis-0.1.9.dist-info/licenses/LICENSE
mcp_server_sis-0.1.9.dist-info/METADATA
mcp_server_sis-0.1.9.dist-info/WHEEL
mcp_server_sis-0.1.9.dist-info/entry_points.txt
mcp_server_sis-0.1.9.dist-info/top_level.txt
mcp_server_sis-0.1.9.dist-info/RECORD
