Metadata-Version: 2.4
Name: mcp-server-sis
Version: 0.1.9
Summary: MCP server for CUHKSZ SIS system
Author-email: LKCY23 <lkcydream@gmail.com>
License: MIT
Keywords: CUHKSZ,SIS,MCP
Classifier: Programming Language :: Python :: 3
Classifier: License :: OSI Approved :: MIT License
Classifier: Operating System :: OS Independent
Requires-Python: >=3.9
License-File: LICENSE
Requires-Dist: pytz>=2024.2
Requires-Dist: requests>=2.30.0
Requires-Dist: urllib3>=2.2.3
Requires-Dist: lxml>=5.3.0
Requires-Dist: pyOpenSSL>=24.2.1
Requires-Dist: httpx>=0.28.1
Requires-Dist: fastmcp>=2.0.0
Requires-Dist: python-dotenv>=1.0.0
Requires-Dist: pydantic>=2.0.0
Dynamic: license-file
